Metadata-Version: 2.1
Name: acv-exp
Version: 1.2.3
Summary: ACV is a library that provides robust and accurate explanations for machine learning models or data
Home-page: https://github.com/salimamoukou/acv00
Author: Salim I. Amoukou
Author-email: salim.ibrahim-amoukou@universite-paris-saclay.fr
License: MIT
License-File: LICENSE
Requires-Dist: numpy (<1.22)
Requires-Dist: scipy
Requires-Dist: scikit-learn
Requires-Dist: matplotlib
Requires-Dist: pandas
Requires-Dist: tqdm
Requires-Dist: ipython
Requires-Dist: seaborn
Requires-Dist: streamlit
Requires-Dist: skranger
Provides-Extra: test
Requires-Dist: xgboost ; extra == 'test'
Requires-Dist: lightgbm ; extra == 'test'
Requires-Dist: catboost ; extra == 'test'
Requires-Dist: pyspark ; extra == 'test'
Requires-Dist: shap ; extra == 'test'
Requires-Dist: rpy2 (==2.9.4) ; extra == 'test'
Requires-Dist: pytest ; extra == 'test'
